[
  {
    "PositionId": "SingleMarketBuyBoth___paper_settlement_validation_single_market___YES___paper_settlement_validation_single_market___NO",
    "GroupKey": "single-market:__paper_settlement_validation_single_market__",
    "Strategy": "SingleMarketBuyBoth",
    "Engine": "SingleMarketBuyBoth",
    "OpenedAtUtc": "2026-06-06T19:53:05.6992829Z",
    "status": "Closed",
    "Quantity": 12,
    "TotalCost": 10.80,
    "CostPerBasket": 0.90,
    "GuaranteedPayout": 12,
    "ExpectedProfit": 1.20,
    "LockedCapital": 0,
    "RealizedPayout": 12.0,
    "RealizedProfit": 1.20,
    "ClosedAtUtc": "2026-06-06T19:53:05.7301924Z",
    "OpenedFromSimulatedFills": true,
    "FillSimulationId": "138433e4d5eb49cf9c6fb60de9942372",
    "legs": [
      {
        "MarketId": "__paper_settlement_validation_single_market__",
        "Question": "Paper Settlement Validation Synthetic Market",
        "Outcome": "YES",
        "Price": 0.45,
        "Quantity": 12,
        "Notional": 5.40
      },
      {
        "MarketId": "__paper_settlement_validation_single_market__",
        "Question": "Paper Settlement Validation Synthetic Market",
        "Outcome": "NO",
        "Price": 0.45,
        "Quantity": 12,
        "Notional": 5.40
      }
    ]
  }
]